kcl/__init__.py
kcl/__init__.pyi
kcl/kcl.cpython-313-x86_64-linux-gnu.so
kcl/py.typed
zoo_kcl-0.3.123.dist-info/METADATA
zoo_kcl-0.3.123.dist-info/WHEEL
zoo_kcl-0.3.123.dist-info/RECORD
