Metadata-Version: 2.4
Name: zoo-kcl
Version: 0.3.123
Classifier: Programming Language :: Rust
Classifier: Programming Language :: Python :: Implementation :: CPython
Classifier: Programming Language :: Python :: Implementation :: PyPy
Requires-Dist: pytest ; extra == 'test'
Requires-Dist: pytest-asyncio ; extra == 'test'
Provides-Extra: test
Requires-Python: >=3.11
